hot_potato/__init__.py
hot_potato/potato.py
hot_potato-0.0.1.dist-info/METADATA
hot_potato-0.0.1.dist-info/WHEEL
hot_potato-0.0.1.dist-info/top_level.txt
hot_potato-0.0.1.dist-info/RECORD
