Metadata-Version: 2.1
Name: hot-potato
Version: 0.0.1
Summary: Learning about PyPI and Github versioning
Home-page: UNKNOWN
Author: Jonathan Heng
Author-email: UNKNOWN
License: UNKNOWN
Platform: UNKNOWN
Classifier: Programming Language :: Python :: 3
